[
  { "tracking_number": "397792612571", "purchase_order_id": 18 },
  { "tracking_number": "492534842068", "purchase_order_id": 17 },
  { "tracking_number": "492534842057", "purchase_order_id": 17 },
  { "tracking_number": "493736926301", "purchase_order_id": 9 },
  { "tracking_number": "493736926275", "purchase_order_id": 9 },
  { "tracking_number": "493736926058", "purchase_order_id": 9 },
  { "tracking_number": "TBA328454215101", "purchase_order_id": 35 },
  { "tracking_number": "1ZB8H1030331339550", "purchase_order_id": 36 },
  { "tracking_number": "TBA328428338888", "purchase_order_id": 33 },
  { "tracking_number": "TBA327766755001", "purchase_order_id": 7 },
  { "tracking_number": "TBA327766745651", "purchase_order_id": 7 },
  { "tracking_number": "TBA327766738976", "purchase_order_id": 7 },
  { "tracking_number": "TBA327766739846", "purchase_order_id": 7 },
  { "tracking_number": "1Z462E670396072025", "purchase_order_id": 15 },
  { "tracking_number": "1Z462E670396353605", "purchase_order_id": 15 },
  { "tracking_number": "1Z462E670399378011", "purchase_order_id": 15 },
  { "tracking_number": "492534842046 (master)", "purchase_order_id": 17 },
  { "tracking_number": "492534842079", "purchase_order_id": 17 },
  { "tracking_number": "1Z462E670399609584", "purchase_order_id": 15 },
  { "tracking_number": "1Z462E670395982795", "purchase_order_id": 15 },
  { "tracking_number": "1Z462E670397715552", "purchase_order_id": 15 },
  { "tracking_number": "1Z462E670398431964", "purchase_order_id": 15 },
  { "tracking_number": "1Z462E670395337974", "purchase_order_id": 15 },
  { "tracking_number": "1Z462E670398347538", "purchase_order_id": 15 },
  { "tracking_number": "1Z462E670397972748", "purchase_order_id": 15 },
  { "tracking_number": "1Z462E670396743925", "purchase_order_id": 15 },
  { "tracking_number": "1Z462E670395946075", "purchase_order_id": 15 },
  { "tracking_number": "1Z462E670395753685", "purchase_order_id": 15 },
  { "tracking_number": "1Z462E670399331650", "purchase_order_id": 15 },
  { "tracking_number": "1Z462E670395064063", "purchase_order_id": 15 },
  { "tracking_number": "1Z462E670396411631", "purchase_order_id": 15 },
  { "tracking_number": "1Z462E670396960128", "purchase_order_id": 15 },
  { "tracking_number": "1Z462E670399635733", "purchase_order_id": 15 },
  { "tracking_number": "1Z462E670397490116", "purchase_order_id": 15 },
  { "tracking_number": "1Z462E670397822892", "purchase_order_id": 15 },
  { "tracking_number": "1Z462E670398649702", "purchase_order_id": 15 },
  { "tracking_number": "1Z462E670395652945", "purchase_order_id": 15 },
  { "tracking_number": "1Z462E670396932846", "purchase_order_id": 15 },
  { "tracking_number": "492534842080", "purchase_order_id": 17 },
  { "tracking_number": "1ZB8H1030331339550", "purchase_order_id": 37 },
  { "tracking_number": "TBA328124149188", "purchase_order_id": 27 },
  { "tracking_number": "1Z4064140398695021", "purchase_order_id": 34 },
  { "tracking_number": "TBA328470668987", "purchase_order_id": 32 },
  { "tracking_number": "TBA328457117959", "purchase_order_id": 32 }
]